MANIFEST.in
README.md
Requirements.txt
setup.py
qtk/__init__.py
qtk/common.py
qtk/controller.py
qtk/converters.py
qtk/fields.py
qtk/templates.py
qtk.egg-info/PKG-INFO
qtk.egg-info/SOURCES.txt
qtk.egg-info/dependency_links.txt
qtk.egg-info/not-zip-safe
qtk.egg-info/requires.txt
qtk.egg-info/top_level.txt
qtk/conventions/__init__.py
qtk/conventions/common.py
qtk/conventions/curves.py
qtk/conventions/govtbonds.py
qtk/conventions/swaptions.py
qtk/creators/__init__.py
qtk/creators/bonds.py
qtk/creators/common.py
qtk/creators/engine.py
qtk/creators/indexes.py
qtk/creators/models.py
qtk/creators/options.py
qtk/creators/processes.py
qtk/creators/reports.py
qtk/creators/utils.py
qtk/creators/volatilitytermstructure.py
qtk/creators/yieldtermstructure.py
qtk/data/__init__.py
qtk/data/bbg/__init__.py
qtk/data/bbg/defs.py
qtk/data/bbg/ircurves.py
qtk/data/bbg/mapper.py
qtk/data/bbg/requesthandler.py
qtk/data/bbg/tickers.py
qtk/data/bbg/utils.py
test/__init__.py
test/test_blackvols.py
test/test_controller.py
test/test_conventions.py
test/test_converters.py
test/test_curves.py
test/test_indexes.py
test/test_models.py
test/test_options.py
test/test_reports.py