Metadata-Version: 1.1
Name: qtk
Version: 0.1.3
Summary: A QuantLib Python ToolKit
Home-page: https://github.com/gouthambs/qtk-python
Author: Goutham Balaraman
Author-email: gouthaman.balaraman@gmail.com
License: MIT
Platform: any
Classifier: Development Status :: 4 - Beta
Classifier: Environment :: Console
Classifier: Intended Audience :: Developers
Classifier: Intended Audience :: End Users/Desktop
Classifier: License :: OSI Approved :: MIT License
Classifier: Operating System :: OS Independent
Classifier: Programming Language :: Python
Classifier: Programming Language :: Python :: 2
Classifier: Programming Language :: Python :: 2.7
Classifier: Topic :: Scientific/Engineering
Classifier: Topic :: Software Development :: Libraries :: Python Modules
